LICENSE
README.md
setup.cfg
setup.py
scratch_implemented/__init__.py
scratch_implemented/classifiers.py
scratch_implemented/data_processing.py
scratch_implemented/linear_algebra.py
scratch_implemented/metrics.py
scratch_implemented/regressors.py
scratch_implemented.egg-info/PKG-INFO
scratch_implemented.egg-info/SOURCES.txt
scratch_implemented.egg-info/dependency_links.txt
scratch_implemented.egg-info/requires.txt
scratch_implemented.egg-info/top_level.txt